n8ntools/__init__.py
n8ntools/n8n_mod.py
n8ntools/n8n_utils.py
n8ntools-0.10.0.dist-info/licenses/LICENSE
n8ntools-0.10.0.dist-info/METADATA
n8ntools-0.10.0.dist-info/WHEEL
n8ntools-0.10.0.dist-info/top_level.txt
n8ntools-0.10.0.dist-info/RECORD
