Metadata-Version: 2.4
Name: n8ntools
Version: 0.10.0
Summary: n8ntools
Author: n8ntools
License: MIT
Classifier: Programming Language :: Python :: 3
Classifier: License :: OSI Approved :: MIT License
Classifier: Operating System :: OS Independent
Requires-Python: >=3.11
License-File: LICENSE
Dynamic: license-file
